audio_transcribe/__init__.py
audio_transcribe/cli.py
audio_transcribe/main.py
audio_transcribe/setup.py
audio_transcribe/core/__init__.py
audio_transcribe/core/models.py
audio_transcribe/core/transcriber.py
audio_transcribe/core/utils.py
audio_transcribe-0.1.0.dist-info/licenses/LICENSE.md
audio_transcribe-0.1.0.dist-info/METADATA
audio_transcribe-0.1.0.dist-info/WHEEL
audio_transcribe-0.1.0.dist-info/entry_points.txt
audio_transcribe-0.1.0.dist-info/top_level.txt
audio_transcribe-0.1.0.dist-info/RECORD
