Metadata-Version: 2.4
Name: audio_transcribe
Version: 0.1.0
Summary: A command-line tool for transcribing audio files using OpenAI's Whisper model
Home-page: https://github.com/yourusername/audio_transcribe
Author: Your Name
Author-email: samurmaykrr <towha@tutanota.com>
License: MIT
Project-URL: Bug Reports, https://github.com/samurmaykrr/audio_transcribe/issues
Project-URL: Source, https://github.com/samurmaykrr/audio_transcribe
Keywords: audio,transcription,whisper,openai,speech-to-text
Requires-Python: >=3.7
License-File: LICENSE.md
Requires-Dist: openai-whisper
Requires-Dist: typer
Requires-Dist: rich
Dynamic: author
Dynamic: home-page
Dynamic: license-file
Dynamic: requires-python
